ChiTH/__init__.py
ChiTH/lib2.py
ChiTH-0.2.dist-info/METADATA
ChiTH-0.2.dist-info/WHEEL
ChiTH-0.2.dist-info/top_level.txt
ChiTH-0.2.dist-info/RECORD
