Metadata-Version: 2.1
Name: ChiTH
Version: 0.2
Summary: Taiwan No. 1
Home-page: http://github.com/storborg/ChiTH
Author: jonathan
Author-email: flyingcircus@example.com
License: MIT
Platform: UNKNOWN
